lemmagen3-3.5.1.dist-info/WHEEL
lemmagen3-3.5.1.dist-info/top_level.txt
lemmagen3-3.5.1.dist-info/RECORD
lemmagen3-3.5.1.dist-info/LICENSE
lemmagen3-3.5.1.dist-info/METADATA
lemmagen3/_lemmagen.cpython-312-x86_64-linux-gnu.so
lemmagen3/__init__.py
lemmagen3/cpp/definitions.h
lemmagen3/cpp/lemmagen.cpp
lemmagen3/models/sk.bin
lemmagen3/models/et.bin
lemmagen3/models/sr.bin
lemmagen3/models/pl.bin
lemmagen3/models/cs.bin
lemmagen3/models/mk.bin
lemmagen3/models/uk.bin
lemmagen3/models/hr.bin
lemmagen3/models/fa.bin
lemmagen3/models/ro.bin
lemmagen3/models/it.bin
lemmagen3/models/es.bin
lemmagen3/models/fr.bin
lemmagen3/models/ru.bin
lemmagen3/models/en.bin
lemmagen3/models/de.bin
lemmagen3/models/hu.bin
lemmagen3/models/bg.bin
lemmagen3/models/sl.bin
