Metadata-Version: 2.1
Name: lemmagen3
Version: 3.5.1
Summary: A Python2/3 wrapper for Lemmagen lemmatizer supporting 19 languages.
Home-page: https://github.com/vpodpecan/lemmagen3/
Author: Vid Podpecan
Author-email: vid.podpecan@ijs.si
Classifier: Operating System :: OS Independent
Classifier: Programming Language :: Python
Classifier: Programming Language :: Python :: 2
Classifier: Programming Language :: Python :: 3
Classifier: Topic :: Scientific/Engineering :: Information Analysis
Classifier: Topic :: Software Development :: Libraries
License-File: LICENSE
Requires-Dist: pybind11 >=2.4
